nexus_aidos/__init__.py
nexus_aidos/cache/__init__.py
nexus_aidos/cache/semantic_cache.py
nexus_aidos/chains/__init__.py
nexus_aidos/chains/rag_chain.py
nexus_aidos/config/__init__.py
nexus_aidos/config/settings.py
nexus_aidos/core/__init__.py
nexus_aidos/core/engine.py
nexus_aidos/core/pipeline.py
nexus_aidos/memory/__init__.py
nexus_aidos/memory/redis_memory.py
nexus_aidos/retrieval/__init__.py
nexus_aidos/retrieval/embeddings.py
nexus_aidos/retrieval/retrievers.py
nexus_aidos/utils/__init__.py
nexus_aidos/utils/logging.py
nexus_aidos/utils/workspace.py
nexus_aidos_brain-0.1.0.dist-info/licenses/LICENSE
nexus_aidos_brain-0.1.0.dist-info/METADATA
nexus_aidos_brain-0.1.0.dist-info/WHEEL
nexus_aidos_brain-0.1.0.dist-info/entry_points.txt
nexus_aidos_brain-0.1.0.dist-info/top_level.txt
nexus_aidos_brain-0.1.0.dist-info/RECORD
