Metadata-Version: 2.4
Name: nexus-aidos-brain
Version: 0.1.0
Summary: Core Conversational AI Engine for the Nexus Ecosystem
Home-page: https://github.com/nexusaihub/NEXUS-AIDOS-BRAIN
Author: Nexus AI Hub Team
Author-email: support@nexusaihub.com
Classifier: Development Status :: 3 - Alpha
Classifier: Intended Audience :: Developers
Classifier: Topic :: Software Development :: Libraries :: Python Modules
Classifier: Topic :: Scientific/Engineering :: Artificial Intelligence
Classifier: License :: OSI Approved :: MIT License
Classifier: Programming Language :: Python :: 3
Classifier: Programming Language :: Python :: 3.8
Classifier: Programming Language :: Python :: 3.9
Classifier: Programming Language :: Python :: 3.10
Classifier: Programming Language :: Python :: 3.11
Requires-Python: >=3.8
License-File: LICENSE
Requires-Dist: langchain<0.2.0,>=0.1.20
Requires-Dist: langchain-core<0.2.0,>=0.1.52
Requires-Dist: langchain-community<0.1.0,>=0.0.38
Requires-Dist: langchain-openai<0.2.0,>=0.1.7
Requires-Dist: langgraph<0.1.0,>=0.0.55
Requires-Dist: qdrant-client<2.0.0,>=1.7.0
Requires-Dist: sentence-transformers<4.0.0,>=3.0.0
Requires-Dist: redis[hiredis]<6.0.0,>=5.0.0
Requires-Dist: numpy<2.0.0,>=1.26.0
Requires-Dist: scikit-learn<2.0.0,>=1.5.0
Requires-Dist: tiktoken<1.0.0,>=0.5.0
Requires-Dist: requests<3.0.0,>=2.31.0
Requires-Dist: certifi>=2024.0.0
Provides-Extra: dev
Requires-Dist: pytest>=7.0.0; extra == "dev"
Requires-Dist: pytest-cov>=4.0.0; extra == "dev"
Requires-Dist: black>=23.0.0; extra == "dev"
Requires-Dist: flake8>=6.0.0; extra == "dev"
Requires-Dist: mypy>=1.0.0; extra == "dev"
Provides-Extra: docs
Requires-Dist: sphinx>=6.0.0; extra == "docs"
Requires-Dist: sphinx-rtd-theme>=1.0.0; extra == "docs"
Dynamic: author
Dynamic: author-email
Dynamic: classifier
Dynamic: description
Dynamic: description-content-type
Dynamic: home-page
Dynamic: license-file
Dynamic: provides-extra
Dynamic: requires-dist
Dynamic: requires-python
Dynamic: summary
